{
  "type_description_msg": {
    "type_description": {
      "type_name": "logitech_msgs/msg/Controller",
      "fields": [
        {
          "name": "motor_value",
          "type": {
            "type_id": 6,
            "capacity": 0,
            "string_capacity": 0,
            "nested_type_name": ""
          },
          "default_value": ""
        },
        {
          "name": "servop",
          "type": {
            "type_id": 6,
            "capacity": 0,
            "string_capacity": 0,
            "nested_type_name": ""
          },
          "default_value": ""
        },
        {
          "name": "servomid",
          "type": {
            "type_id": 6,
            "capacity": 0,
            "string_capacity": 0,
            "nested_type_name": ""
          },
          "default_value": ""
        }
      ]
    },
    "referenced_type_descriptions": []
  },
  "type_hashes": [
    {
      "type_name": "logitech_msgs/msg/Controller",
      "hash_string": "RIHS01_cb4424044460d163b01a94f88346538e9a79940196358c9123f1b61abfd85ed1"
    }
  ]
}